biobb_gromacs/__init__.py
biobb_gromacs/py.typed
biobb_gromacs/gromacs/__init__.py
biobb_gromacs/gromacs/common.py
biobb_gromacs/gromacs/convert_tpr.py
biobb_gromacs/gromacs/editconf.py
biobb_gromacs/gromacs/genion.py
biobb_gromacs/gromacs/genrestr.py
biobb_gromacs/gromacs/gmxselect.py
biobb_gromacs/gromacs/grompp.py
biobb_gromacs/gromacs/grompp_mdrun.py
biobb_gromacs/gromacs/make_ndx.py
biobb_gromacs/gromacs/mdrun.py
biobb_gromacs/gromacs/pdb2gmx.py
biobb_gromacs/gromacs/solvate.py
biobb_gromacs/gromacs/trjcat.py
biobb_gromacs/gromacs_extra/__init__.py
biobb_gromacs/gromacs_extra/append_ligand.py
biobb_gromacs/gromacs_extra/ndx2resttop.py
biobb_gromacs/test/__init__.py
biobb_gromacs-5.2.0.dist-info/licenses/LICENSE
biobb_gromacs-5.2.0.dist-info/METADATA
biobb_gromacs-5.2.0.dist-info/WHEEL
biobb_gromacs-5.2.0.dist-info/entry_points.txt
biobb_gromacs-5.2.0.dist-info/top_level.txt
biobb_gromacs-5.2.0.dist-info/RECORD
